samply/__init__.py
samply/ball.py
samply/directional.py
samply/hypercube.py
samply/nullspace.py
samply/shape.py
samply/subspace.py
samply/tests/__init__.py
samply/tests/test_ball.py
samply/tests/test_direction.py
samply/tests/test_hypercube.py
samply/tests/test_nullspace.py
samply/tests/test_shape.py
samply/tests/test_subspace.py
samply-0.1.2.dist-info/LICENSE
samply-0.1.2.dist-info/METADATA
samply-0.1.2.dist-info/WHEEL
samply-0.1.2.dist-info/top_level.txt
samply-0.1.2.dist-info/RECORD
