Metadata-Version: 2.1
Name: samply
Version: 0.1.2
Summary: A library for computing samplings in arbitrary dimensions
Author-email: Dan Maljovec <maljovec002@gmail.com>
Project-URL: Documentation, https://samply.readthedocs.io/en/latest/
Project-URL: Source, https://github.com/maljovec/samply
Classifier: Development Status :: 3 - Alpha
Classifier: Intended Audience :: Science/Research
Classifier: License :: OSI Approved :: BSD License
Classifier: Programming Language :: Python :: 3
Classifier: Topic :: Scientific/Engineering :: Mathematics
Requires-Python: >=3.7
License-File: LICENSE
Requires-Dist: scipy
Requires-Dist: numpy
Requires-Dist: scikit-learn
Requires-Dist: pyDOE
Requires-Dist: ghalton (<0.6.2)
